indexs.py
ljc-alpha.py
setup.py
alphaseeker.egg-info/PKG-INFO
alphaseeker.egg-info/SOURCES.txt
alphaseeker.egg-info/dependency_links.txt
alphaseeker.egg-info/top_level.txt