Metadata-Version: 1.0
Name: alphaseeker
Version: 0.0.2
Summary: Alpha like ratios calculate ,based on the chinese stock market for now
Home-page: UNKNOWN
Author: Jiacheng Liu
Author-email: Kevin_ljc@foxmail.com
License: UNKNOWN
Platform: UNKNOWN
